LICENSE.txt
README.md
setup.cfg
setup.py
cluspy/__init__.py
cluspy/functions.py
cluspy.egg-info/PKG-INFO
cluspy.egg-info/SOURCES.txt
cluspy.egg-info/dependency_links.txt
cluspy.egg-info/requires.txt
cluspy.egg-info/top_level.txt